[{"username":"test","password":"lol","first-name":"The Ultimate","last-name":"Warrior","email":"lol.test@emptyemail.com","post-address":"1\/1, First St., Test City, NA, 1111","delivery-address":"100, Post St., Test City, NA, 1111","phone":"08004035071"},{"username":"slithers","password":"the snake","first-name":"a","last-name":"b","email":"slithers@snakemail.com","post-address":"c 21","delivery-address":"d 41","phone":"5555555"},{"username":"hello","password":"my, man","first-name":"","last-name":"","email":"","post-address":"","delivery-address":"","phone":""},{"username":"lala","password":"lalala","first-name":"","last-name":"","email":"snakeman@gothamcity.co.nz","post-address":"","delivery-address":"","phone":""},{"username":"slide","password":"lolmysnake","first-name":"","last-name":"","email":"slither@snakeacademy.co.nz","post-address":"","delivery-address":"","phone":""}]
